roxasauth.py
roxasauth-1.2.0.dist-info/DESCRIPTION.rst
roxasauth-1.2.0.dist-info/METADATA
roxasauth-1.2.0.dist-info/RECORD
roxasauth-1.2.0.dist-info/WHEEL
roxasauth-1.2.0.dist-info/metadata.json
roxasauth-1.2.0.dist-info/top_level.txt
